{"last":86,"today":23,"tickets":[{"number":54,"desktop":null},{"number":55,"desktop":null},{"number":56,"desktop":null},{"number":57,"desktop":null},{"number":58,"desktop":null},{"number":59,"desktop":null},{"number":60,"desktop":null},{"number":61,"desktop":null},{"number":62,"desktop":null},{"number":63,"desktop":null},{"number":64,"desktop":null},{"number":65,"desktop":null},{"number":66,"desktop":null},{"number":67,"desktop":null},{"number":68,"desktop":null},{"number":69,"desktop":null},{"number":70,"desktop":null},{"number":71,"desktop":null},{"number":72,"desktop":null},{"number":73,"desktop":null},{"number":74,"desktop":null},{"number":75,"desktop":null},{"number":76,"desktop":null},{"number":77,"desktop":null},{"number":78,"desktop":null},{"number":79,"desktop":null},{"number":80,"desktop":null},{"number":81,"desktop":null},{"number":82,"desktop":null},{"number":83,"desktop":null},{"number":84,"desktop":null},{"number":85,"desktop":null},{"number":86,"desktop":null}],"anserweredTickets":[{"number":53,"desktop":"1"},{"number":52,"desktop":"1"},{"number":51,"desktop":"1"},{"number":50,"desktop":"1"}]}